{
  "$schema": "./_projects.schema.json",
  "title": "Cuida",
  "description": "Plataforma para la visibilidad de Refugios Animales de Cúcuta Colombia. Desarrollo de producto completo.",
  "bento_area": "quaternary",
  "demo": "https://www.figma.com/proto/422k9OQmvHMQZq9JQ3Lzdd/Cuida?node-id=1113-10407&t=VrUm6n3CQznHstWK-1&starting-point-node-id=1113%3A10407&show-proto-sidebar=1",
  "code": "https://github.com/andrescasa-dev/cuida-frontend",
  "read_more": {
    "href": "blogs/cuida",
    "label": "Conoce su historia"
  },
  "technologies": [
    {
      "category": "frontend",
      "items": [
        {
          "name": "TypeScript",
          "icon": "TypeScript"
        },
        {
          "name": "React",
          "icon": "React"
        },
        {
          "name": "NextJS app router",
          "icon": "NextJS14"
        },
        {
          "name": "Tailwind",
          "icon": "Tailwind"
        },
        {
          "name": "Html5",
          "icon": "Html"
        },
        {
          "name": "RadixUI",
          "icon": "RadixUI"
        }
      ]
    },
    {
      "category": "backend",
      "items": [
        {
          "name": "Strapi",
          "icon": "Strapi"
        },
        {
          "name": "JavaScript",
          "icon": "JavaScript"
        }
      ]
    },
    {
      "category": "design",
      "items": [
        {
          "name": "Figma",
          "icon": "Figma"
        },
        {
          "name": "Ux Design",
          "icon": "UxDesign"
        }
      ]
    }
  ],
  "main_features": [
    "Diseñado a partir de investigación de mercado.",
    "Necesidades del usuario como pieza central.",
    "Consideración de Identidad de marca.",
    "Investigación de servicios y planeación de MVP.",
    "Uso de la mitología moderna Design thinking",
    "Aprendizaje continuo y resiliente."
  ],
  "challenges": [
    {
      "title": "Desconocimiento de necesidades de Refugios",
      "solution": "elaboré una entrevista a una líder de refugios junto con una investigación de mercado."
    },
    {
      "title": "Crear Design system profesional",
      "solution": "Investigué y entendí cómo estaban hechos los Design System consolidados, tales como Material UI y Strapi DS, luego realicé una auditoría a la primera versión de mi diseño."
    },
    {
      "title": "Definir el MVP",
      "solution": "Junto con la Universidad Simón Bolívar logré definir las ideas que mayor impacto iban a tener en los refugios."
    },
    {
      "title": "Comunicar en el diseño los valores de Cuida",
      "solution": "Estudié lo necesario de UX/UI y Branding para garantizar que la interfaz transmita dichos valores en todo momento."
    }
  ],
  "what_i_learned": [
    "Entendí el proceso completo de un producto digital, desde el branding hasta el desarrollo.",
    "Comprendí que la consistencia y una clara jerarquía son más importantes que los detalles visuales en una interfaz gráfica.",
    "Entendí que un buen software se basa en la mejora continua, no en la perfección inicial.",
    "Mejoré mis habilidades en Figma para diseñar prototipos de baja y alta fidelidad."
  ]
}